intec_units-0.0.5.data/purelib/intec/units/__init__.py
intec_units-0.0.5.data/purelib/intec/units/construct.py
intec_units-0.0.5.data/purelib/intec/units/extra.py
intec_units-0.0.5.data/purelib/intec/units/intecunits.pyd
intec_units-0.0.5.data/purelib/intec/units/photonic.py
intec_units-0.0.5.data/purelib/intec/units/si.py
intec_units-0.0.5.data/purelib/intec/units/test/test_units.py
intec_units-0.0.5.dist-info/METADATA
intec_units-0.0.5.dist-info/WHEEL
intec_units-0.0.5.dist-info/top_level.txt
intec_units-0.0.5.dist-info/RECORD
