Metadata-Version: 2.1
Name: intec-units
Version: 0.0.5
Summary: Physical units library
Home-page: https://bitbucket.org/zmic/intec-units
Author: Michael Vanslembrouck
License: MIT
Platform: UNKNOWN
Classifier: Development Status :: 3 - Alpha
Requires-Python: >=3.4
